LICENSE
MANIFEST.in
README.txt
bootstrap.py
buildout.cfg
setup.cfg
setup.py
tox.ini
src/sphinxcontrib_phpautodoc.py
src/phply/__init__.py
src/phply/phpast.py
src/phply/phplex.py
src/phply/phpparse.py
src/phply/pythonast.py
src/tk.phpautodoc.egg-info/PKG-INFO
src/tk.phpautodoc.egg-info/SOURCES.txt
src/tk.phpautodoc.egg-info/dependency_links.txt
src/tk.phpautodoc.egg-info/requires.txt
src/tk.phpautodoc.egg-info/top_level.txt
tests/run_tests.py
tests/inputs/arguments.php
tests/inputs/class.php
tests/inputs/function.php
tests/inputs/interface.php
tests/inputs/private_class.php
tests/inputs/private_interface.php
tests/inputs/syntax_error.php
tests/inputs/undoc_class.php
tests/inputs/undoc_interface.php
tests/inputs/phpautoclass/class_basic.rst
tests/inputs/phpautoclass/class_content.rst
tests/inputs/phpautoclass/class_members.rst
tests/inputs/phpautoclass/class_members_and_content.rst
tests/inputs/phpautoclass/class_members_and_undoc.rst
tests/inputs/phpautoclass/class_undoc.rst
tests/inputs/phpautoclass/interface_basic.rst
tests/inputs/phpautoclass/interface_content.rst
tests/inputs/phpautoclass/interface_members.rst
tests/inputs/phpautoclass/interface_members_and_content.rst
tests/inputs/phpautoclass/interface_members_and_undoc.rst
tests/inputs/phpautoclass/interface_undoc.rst
tests/inputs/phpautoclass/private_class_basic.rst
tests/inputs/phpautoclass/private_interface_basic.rst
tests/inputs/phpautoclass/undoc_class_basic.rst
tests/inputs/phpautoclass/undoc_interface_basic.rst
tests/inputs/phpautofunction/function_basic.rst
tests/inputs/phpautofunction/private_function_basic.rst
tests/inputs/phpautofunction/undoc_function_basic.rst
tests/inputs/phpautomodule/class_basic.rst
tests/inputs/phpautomodule/class_members.rst
tests/inputs/phpautomodule/class_members_and_undoc.rst
tests/inputs/phpautomodule/class_undoc.rst
tests/inputs/phpautomodule/function_arguments.rst
tests/inputs/phpautomodule/function_basic.rst
tests/inputs/phpautomodule/function_undoc.rst
tests/inputs/phpautomodule/interface_basic.rst
tests/inputs/phpautomodule/interface_members.rst
tests/inputs/phpautomodule/interface_members_and_undoc.rst
tests/inputs/phpautomodule/interface_undoc.rst
