Metadata-Version: 1.0
Name: tk.phpautodoc
Version: 1.2.1
Summary: sample implementation of phpdocumentor using sphinx
Home-page: https://bitbucket.org/tk0miya/tk.phpautodoc
Author: Takeshi Komiya
Author-email: i.tkomiya at gmail.com
License: Apache License 2.0
Platform: UNKNOWN
